Workbook
Name aporte: APP!$D$17
Name patrimonio: APP!$D$20
Name qtd_anos: APP!$D$18
Name rendimento_carteira: APP!$D$12
Name salario: APP!$D$11
Name sugestao_investimento: APP!$D$13
Name taxa_mensal: APP!$D$19

Sheet APP
B10: CONFIGURAÇÕES
B11: Salário | D11: 4200
B12: Rendimento Carteira | D12: 0.006
B13: Sugestão de Investimento | D13: =D11*30% -> 1260
B16: INVESTIMENTO MENSAL
B17: Quanto investir por mês? | D17: 1260
B18: Por quantos anos? | D18: 10
B19: Taxa de Rendimento Mensal? | D19: 0.01079
B20: Patrimônio Acumulado? | D20: =FV(taxa_mensal,qtd_anos*12,aporte*-1) -> 306538.11
B21: Dividendos Mensais? | D21: =patrimonio*rendimento_carteira -> 1839.2286
B24: CENÁRIOS | D24: DIVIDENDO
A25: 2 | B25: Quanto em 2 Anos | C25: =FV($D$19,$A25*12,$D$17*-1) -> 34306.81 | D25: =C25*rendimento_carteira -> 205.84086
A26: 5 | B26: Quanto em 5 Anos | C26: =FV($D$19,$A26*12,$D$17*-1) -> 105558.91 | D26: =C26*rendimento_carteira -> 633.35347
A27: 10 | B27: Quanto em 10 Anos | C27: =FV($D$19,$A27*12,$D$17*-1) -> 306538.11 | D27: =C27*rendimento_carteira -> 1839.2286
A28: 20 | B28: Quanto em 20 Anos | C28: =FV($D$19,$A28*12,$D$17*-1) -> 1417750 | D28: =C28*rendimento_carteira -> 8506.4999
A29: 30 | B29: Quanto em 30 Anos | C29: =FV($D$19,$A29*12,$D$17*-1) -> 5445933.8 | D29: =C29*rendimento_carteira -> 32675.603
B33: PERFIL | C33: MODERADO
B34: Valor a ser Investido por Mês | C34: =aporte -> 1260
B37: TIPO DE FII | C37: PERCENTUAL SUGERIDO | D37: VALORES
B38: Papel | C38: =VLOOKUP($C$33&"-"&B38,Planilha2!$A$2:$D$20,4,FALSE) -> 0.32 | D38: =C38*$C$34 -> 403.2
B39: Tijolo | C39: =VLOOKUP($C$33&"-"&B39,Planilha2!$A$2:$D$20,4,FALSE) -> 0.4 | D39: =C39*$C$34 -> 504
B40: Híbridos | C40: =VLOOKUP($C$33&"-"&B40,Planilha2!$A$2:$D$20,4,FALSE) -> 0.08 | D40: =C40*$C$34 -> 100.8
B41: FOFs | C41: =VLOOKUP($C$33&"-"&B41,Planilha2!$A$2:$D$20,4,FALSE) -> 0.1 | D41: =C41*$C$34 -> 126
B42: Desenvolvimento | C42: =VLOOKUP($C$33&"-"&B42,Planilha2!$A$2:$D$20,4,FALSE) -> 0.05 | D42: =C42*$C$34 -> 63
B43: Hotelarias | C43: =VLOOKUP($C$33&"-"&B43,Planilha2!$A$2:$D$20,4,FALSE) -> 0.05 | D43: =C43*$C$34 -> 63
D44: =SUM(D38:D43) -> 1260

Sheet Planilha2
A2: CHAVE | B2: PERFIL | C2: TIPO DE FII | D2: %
A3: =B3&"-"&C3 -> CONSERVADOR-Papel | B3: CONSERVADOR | C3: Papel | D3: 0.3
A4: =B4&"-"&C4 -> CONSERVADOR-Tijolo | B4: CONSERVADOR | C4: Tijolo | D4: 0.5
A5: =B5&"-"&C5 -> CONSERVADOR-Híbridos | B5: CONSERVADOR | C5: Híbridos | D5: 0.1
A6: =B6&"-"&C6 -> CONSERVADOR-FOFs | B6: CONSERVADOR | C6: FOFs | D6: 0.1
A7: =B7&"-"&C7 -> CONSERVADOR-Desenvolvimento | B7: CONSERVADOR | C7: Desenvolvimento | D7: 0
A8: =B8&"-"&C8 -> CONSERVADOR-Hotelarias | B8: CONSERVADOR | C8: Hotelarias | D8: 0
A9: =B9&"-"&C9 -> MODERADO-Papel | B9: MODERADO | C9: Papel | D9: 0.32
A10: =B10&"-"&C10 -> MODERADO-Tijolo | B10: MODERADO | C10: Tijolo | D10: 0.4
A11: =B11&"-"&C11 -> MODERADO-Híbridos | B11: MODERADO | C11: Híbridos | D11: 0.08
A12: =B12&"-"&C12 -> MODERADO-FOFs | B12: MODERADO | C12: FOFs | D12: 0.1
A13: =B13&"-"&C13 -> MODERADO-Desenvolvimento | B13: MODERADO | C13: Desenvolvimento | D13: 0.05
A14: =B14&"-"&C14 -> MODERADO-Hotelarias | B14: MODERADO | C14: Hotelarias | D14: 0.05
... A20: =B20&"-"&C20 -> AGRESSIVO-Hotelarias | B20: AGRESSIVO | C20: Hotelarias | D20: 0.1
